pyhpecw7/__init__.py
pyhpecw7/comware.py
pyhpecw7/errors.py
pyhpecw7/features/__init__.py
pyhpecw7/features/cleanerase.py
pyhpecw7/features/config.py
pyhpecw7/features/errors.py
pyhpecw7/features/facts.py
pyhpecw7/features/file_copy.py
pyhpecw7/features/install_os.py
pyhpecw7/features/interface.py
pyhpecw7/features/ipinterface.py
pyhpecw7/features/irf.py
pyhpecw7/features/l2vpn.py
pyhpecw7/features/neighbor.py
pyhpecw7/features/ping.py
pyhpecw7/features/portchannel.py
pyhpecw7/features/reboot.py
pyhpecw7/features/switchport.py
pyhpecw7/features/vlan.py
pyhpecw7/features/vrrp.py
pyhpecw7/features/vxlan.py
pyhpecw7/utils/__init__.py
pyhpecw7/utils/validate.py
pyhpecw7/utils/network/__init__.py
pyhpecw7/utils/templates/__init__.py
pyhpecw7/utils/templates/cli.py
pyhpecw7/utils/templates/textfsm_temps/__init__.py
pyhpecw7/utils/templates/textfsm_temps/tunnel.tmpl
pyhpecw7/utils/templates/textfsm_temps/vrrp.tmpl
pyhpecw7/utils/xml/__init__.py
pyhpecw7/utils/xml/lib.py
pyhpecw7/utils/xml/namespaces.py
pyhpecw7-0.0.10.dist-info/METADATA
pyhpecw7-0.0.10.dist-info/RECORD
pyhpecw7-0.0.10.dist-info/WHEEL
pyhpecw7-0.0.10.dist-info/top_level.txt
